antevresto_lib/MyTables.py
antevresto_lib/__init__.py
antevresto_lib-0.1.2.dist-info/METADATA
antevresto_lib-0.1.2.dist-info/WHEEL
antevresto_lib-0.1.2.dist-info/top_level.txt
antevresto_lib-0.1.2.dist-info/RECORD
