Metadata-Version: 2.4
Name: antevresto-lib
Version: 0.1.2
Summary: Shared utilities for Antevresto
Author: John Sk
Requires-Python: >=3.9
